airflow/providers/salesforce/__init__.py
airflow/providers/salesforce/get_provider_info.py
airflow/providers/salesforce/version_compat.py
airflow/providers/salesforce/hooks/__init__.py
airflow/providers/salesforce/hooks/salesforce.py
airflow/providers/salesforce/operators/__init__.py
airflow/providers/salesforce/operators/bulk.py
airflow/providers/salesforce/operators/salesforce_apex_rest.py
apache_airflow_providers_salesforce-5.12.2.dist-info/entry_points.txt
apache_airflow_providers_salesforce-5.12.2.dist-info/licenses/LICENSE
apache_airflow_providers_salesforce-5.12.2.dist-info/licenses/NOTICE
apache_airflow_providers_salesforce-5.12.2.dist-info/WHEEL
apache_airflow_providers_salesforce-5.12.2.dist-info/METADATA
apache_airflow_providers_salesforce-5.12.2.dist-info/RECORD
